<?xml version="1.0" encoding="UTF-8"?>
<faces-config version="2.0" xmlns="http://java.sun.com/xml/ns/javaee" xmlns:xi="http://www.w3.org/2001/XInclude" xmlns:xsi="http://www.w3.org/2001/XMLSchema-instance" xsi:schemaLocation="http://java.sun.com/xml/ns/javaee http://java.sun.com/xml/ns/javaee/web-facesconfig_2_0.xsd">
	<managed-bean>
		<managed-bean-name>menuListener</managed-bean-name>
		<managed-bean-class>za.co.idea.web.util.MenuListener</managed-bean-class>
		<managed-bean-scope>session</managed-bean-scope>
	</managed-bean>
	<managed-bean>
		<managed-bean-name>adminBean</managed-bean-name>
		<managed-bean-class>za.co.idea.web.ui.AdminController</managed-bean-class>
		<managed-bean-scope>session</managed-bean-scope>
	</managed-bean>
	<managed-bean>
		<managed-bean-name>ideaBean</managed-bean-name>
		<managed-bean-class>za.co.idea.web.ui.IdeaController</managed-bean-class>
		<managed-bean-scope>session</managed-bean-scope>
	</managed-bean>
	<managed-bean>
		<managed-bean-name>imageBean</managed-bean-name>
		<managed-bean-class>za.co.idea.web.ui.ImageController</managed-bean-class>
		<managed-bean-scope>session</managed-bean-scope>
	</managed-bean>
	<managed-bean>
		<managed-bean-name>challengeBean</managed-bean-name>
		<managed-bean-class>za.co.idea.web.ui.ChallengeController</managed-bean-class>
		<managed-bean-scope>session</managed-bean-scope>
	</managed-bean>
	<managed-bean>
		<managed-bean-name>rewardsBean</managed-bean-name>
		<managed-bean-class>za.co.idea.web.ui.RewardsController</managed-bean-class>
		<managed-bean-scope>session</managed-bean-scope>
	</managed-bean>
	<managed-bean>
		<managed-bean-name>claimBean</managed-bean-name>
		<managed-bean-class>za.co.idea.web.ui.ClaimController</managed-bean-class>
		<managed-bean-scope>session</managed-bean-scope>
	</managed-bean>
	<navigation-rule>
		<navigation-case>
			<from-outcome>login</from-outcome>
			<to-view-id>/pages/admin/login.xhtml</to-view-id>
		</navigation-case>
		<navigation-case>
			<from-outcome>home</from-outcome>
			<to-view-id>/pages/home.xhtml</to-view-id>
		</navigation-case>
		<navigation-case>
			<from-outcome>admcu</from-outcome>
			<to-view-id>/pages/admin/createUser.xhtml</to-view-id>
		</navigation-case>
		<navigation-case>
			<from-outcome>admeu</from-outcome>
			<to-view-id>/pages/admin/editUser.xhtml</to-view-id>
		</navigation-case>
		<navigation-case>
			<from-outcome>admvu</from-outcome>
			<to-view-id>/pages/admin/viewUsers.xhtml</to-view-id>
		</navigation-case>
		<navigation-case>
			<from-outcome>admcg</from-outcome>
			<to-view-id>/pages/admin/createGroup.xhtml</to-view-id>
		</navigation-case>
		<navigation-case>
			<from-outcome>admeg</from-outcome>
			<to-view-id>/pages/admin/editGroup.xhtml</to-view-id>
		</navigation-case>
		<navigation-case>
			<from-outcome>admvg</from-outcome>
			<to-view-id>/pages/admin/viewGroups.xhtml</to-view-id>
		</navigation-case>
		<navigation-case>
			<from-outcome>admcf</from-outcome>
			<to-view-id>/pages/admin/createFunction.xhtml</to-view-id>
		</navigation-case>
		<navigation-case>
			<from-outcome>admef</from-outcome>
			<to-view-id>/pages/admin/editFunction.xhtml</to-view-id>
		</navigation-case>
		<navigation-case>
			<from-outcome>admvf</from-outcome>
			<to-view-id>/pages/admin/viewFunction.xhtml</to-view-id>
		</navigation-case>
	</navigation-rule>
	<navigation-rule>
		<navigation-case>
			<from-outcome>ideaci</from-outcome>
			<to-view-id>/pages/idea/create.xhtml</to-view-id>
		</navigation-case>
		<navigation-case>
			<from-outcome>ideaei</from-outcome>
			<to-view-id>/pages/idea/edit.xhtml</to-view-id>
		</navigation-case>
		<navigation-case>
			<from-outcome>ideavi</from-outcome>
			<to-view-id>/pages/idea/view.xhtml</to-view-id>
		</navigation-case>
		<navigation-case>
			<from-outcome>ideasi</from-outcome>
			<to-view-id>/pages/idea/summary.xhtml</to-view-id>
		</navigation-case>
		<navigation-case>
			<from-outcome>ideaui</from-outcome>
			<to-view-id>/pages/user/ideas.xhtml</to-view-id>
		</navigation-case>
	</navigation-rule>
	<navigation-rule>
		<navigation-case>
			<from-outcome>chalcc</from-outcome>
			<to-view-id>/pages/challenge/create.xhtml</to-view-id>
		</navigation-case>
		<navigation-case>
			<from-outcome>chalec</from-outcome>
			<to-view-id>/pages/challenge/edit.xhtml</to-view-id>
		</navigation-case>
		<navigation-case>
			<from-outcome>chalvc</from-outcome>
			<to-view-id>/pages/challenge/view.xhtml</to-view-id>
		</navigation-case>
		<navigation-case>
			<from-outcome>chalsc</from-outcome>
			<to-view-id>/pages/challenge/summary.xhtml</to-view-id>
		</navigation-case>
		<navigation-case>
			<from-outcome>chaluc</from-outcome>
			<to-view-id>/pages/user/challenges.xhtml</to-view-id>
		</navigation-case>
	</navigation-rule>
	<navigation-rule>
		<navigation-case>
			<from-outcome>solcs</from-outcome>
			<to-view-id>/pages/solution/create.xhtml</to-view-id>
		</navigation-case>
		<navigation-case>
			<from-outcome>soles</from-outcome>
			<to-view-id>/pages/solution/edit.xhtml</to-view-id>
		</navigation-case>
		<navigation-case>
			<from-outcome>solvs</from-outcome>
			<to-view-id>/pages/solution/view.xhtml</to-view-id>
		</navigation-case>
		<navigation-case>
			<from-outcome>solss</from-outcome>
			<to-view-id>/pages/solution/summary.xhtml</to-view-id>
		</navigation-case>
		<navigation-case>
			<from-outcome>solus</from-outcome>
			<to-view-id>/pages/user/solutions.xhtml</to-view-id>
		</navigation-case>
	</navigation-rule>
	<navigation-rule>
		<navigation-case>
			<from-outcome>rwcr</from-outcome>
			<to-view-id>/pages/rewards/create.xhtml</to-view-id>
		</navigation-case>
		<navigation-case>
			<from-outcome>rwer</from-outcome>
			<to-view-id>/pages/rewards/edit.xhtml</to-view-id>
		</navigation-case>
		<navigation-case>
			<from-outcome>rwvr</from-outcome>
			<to-view-id>/pages/rewards/store.xhtml</to-view-id>
		</navigation-case>
		<navigation-case>
			<from-outcome>rwur</from-outcome>
			<to-view-id>/pages/user/wishlist.xhtml</to-view-id>
		</navigation-case>
	</navigation-rule>
	<navigation-rule>
		<navigation-case>
			<from-outcome>clmcc</from-outcome>
			<to-view-id>/pages/claim/create.xhtml</to-view-id>
		</navigation-case>
		<navigation-case>
			<from-outcome>clmec</from-outcome>
			<to-view-id>/pages/claim/edit.xhtml</to-view-id>
		</navigation-case>
		<navigation-case>
			<from-outcome>clmvc</from-outcome>
			<to-view-id>/pages/claim/view.xhtml</to-view-id>
		</navigation-case>
		<navigation-case>
			<from-outcome>clmuc</from-outcome>
			<to-view-id>/pages/user/claims.xhtml</to-view-id>
		</navigation-case>
	</navigation-rule>
	<lifecycle>
		<phase-listener>za.co.idea.web.util.SessionPhaseListener</phase-listener>
	</lifecycle>
	<validator>
		<display-name>SocialConnectorValidator</display-name>
		<validator-id>za.co.idea.web.util.SocialConnectorValidator</validator-id>
		<validator-class>za.co.idea.web.util.SocialConnectorValidator</validator-class>
	</validator>
	<application>
		<el-resolver>org.springframework.web.jsf.el.SpringBeanFacesELResolver</el-resolver>
	</application>
</faces-config>